stsw/__init__.py
stsw/py.typed
stsw/_core/__init__.py
stsw/_core/crc32.py
stsw/_core/dtype.py
stsw/_core/header.py
stsw/_core/meta.py
stsw/cli/__init__.py
stsw/cli/__main__.py
stsw/io/__init__.py
stsw/io/fileio.py
stsw/io/mmapwrap.py
stsw/reader/__init__.py
stsw/reader/reader.py
stsw/writer/__init__.py
stsw/writer/writer.py
stsw-1.0.0.dist-info/licenses/LICENSE
stsw-1.0.0.dist-info/METADATA
stsw-1.0.0.dist-info/WHEEL
stsw-1.0.0.dist-info/entry_points.txt
stsw-1.0.0.dist-info/top_level.txt
stsw-1.0.0.dist-info/RECORD
