Metadata-Version: 2.4
Name: stsw
Version: 1.0.0
Summary: The Last-Word Safe-Tensor Stream Suite
Author-email: The stsw Authors <contact@stsw.dev>
License: Apache-2.0
Project-URL: Homepage, https://github.com/stsw-project/stsw
Project-URL: Documentation, https://stsw-project.github.io/stsw
Project-URL: Repository, https://github.com/stsw-project/stsw
Project-URL: Issues, https://github.com/stsw-project/stsw/issues
Project-URL: Changelog, https://github.com/stsw-project/stsw/blob/main/CHANGELOG.md
Keywords: safetensors,streaming,tensor,pytorch,numpy
Classifier: Development Status :: 5 - Production/Stable
Classifier: Intended Audience :: Developers
Classifier: License :: OSI Approved :: Apache Software License
Classifier: Programming Language :: Python :: 3
Classifier: Programming Language :: Python :: 3.9
Classifier: Programming Language :: Python :: 3.10
Classifier: Programming Language :: Python :: 3.11
Classifier: Programming Language :: Python :: 3.12
Classifier: Topic :: Scientific/Engineering :: Artificial Intelligence
Classifier: Typing :: Typed
Requires-Python: >=3.9
License-File: LICENSE
Provides-Extra: torch
Requires-Dist: torch>=1.10.0; extra == "torch"
Provides-Extra: numpy
Requires-Dist: numpy>=1.20.0; extra == "numpy"
Provides-Extra: xxhash
Requires-Dist: xxhash>=3.0.0; extra == "xxhash"
Provides-Extra: rich
Requires-Dist: rich>=13.0.0; extra == "rich"
Provides-Extra: tqdm
Requires-Dist: tqdm>=4.65.0; extra == "tqdm"
Provides-Extra: dev
Requires-Dist: pytest==8.0.0; extra == "dev"
Requires-Dist: pytest-cov==4.1.0; extra == "dev"
Requires-Dist: pytest-xdist==3.5.0; extra == "dev"
Requires-Dist: hypothesis==6.98.0; extra == "dev"
Requires-Dist: coverage[toml]==7.4.0; extra == "dev"
Requires-Dist: pyright==1.1.350; extra == "dev"
Requires-Dist: ruff==0.4.0; extra == "dev"
Requires-Dist: black==24.1.0; extra == "dev"
Requires-Dist: mutmut==2.4.4; extra == "dev"
Requires-Dist: pre-commit==3.6.0; extra == "dev"
Provides-Extra: bench
Requires-Dist: asv>=0.6.4; extra == "bench"
Requires-Dist: psutil>=5.9.0; extra == "bench"
Provides-Extra: docs
Requires-Dist: mkdocs-material>=9.5.0; extra == "docs"
Requires-Dist: mkdocs-exec>=0.4.0; extra == "docs"
Requires-Dist: mkdocstrings[python]>=0.24.0; extra == "docs"
Provides-Extra: all
Requires-Dist: stsw[bench,dev,docs,numpy,rich,torch,tqdm,xxhash]; extra == "all"
Dynamic: license-file
